{
  "timestamp": "2025-09-21T05:36:08Z",
  "run_id": "2025-09-21T053033Z",
  "train": {
    "seed": 42,
    "learning_rate": 0.006047018496816363,
    "entropy_coef": 0.07123566778619919,
    "batch_size": 2359296,
    "minibatch_size": 2359296,
    "max_minibatch_size": 2359296,
    "bptt_horizon": 64,
    "total_timesteps": 200000000
  },
  "env": {
    "num_envs": 24,
    "num_drones": 64
  },
  "vec": {
    "num_envs": 24,
    "num_workers": 24
  },
  "metrics": {
    "success_rate": 0.0,
    "mean_reward": 9.451521158218384,
    "episode_length": 51.065080086390175,
    "collision_rate": 0.004746081540361047,
    "sps": 1405044.1713033589,
    "agent_steps": 276037632,
    "epoch": 85
  }
}